Metadata-Version: 2.4
Name: hypertrial
Version: 0.1.14
Summary: Bitcoin Dollar-Cost Averaging (DCA) Backtest Framework
Home-page: https://github.com/hypertrial/hypertrial
Author: Matt Faltyn
Author-email: matt@trilemmacapital.com
Project-URL: Bug Tracker, https://github.com/hypertrial/hypertrial/issues
Project-URL: Documentation, https://github.com/hypertrial/hypertrial#readme
Project-URL: Source Code, https://github.com/hypertrial/hypertrial
Classifier: Development Status :: 3 - Alpha
Classifier: Intended Audience :: Financial and Insurance Industry
Classifier: Programming Language :: Python :: 3
Classifier: Programming Language :: Python :: 3.6
Classifier: Programming Language :: Python :: 3.7
Classifier: Programming Language :: Python :: 3.8
Classifier: Programming Language :: Python :: 3.9
Classifier: Programming Language :: Python :: 3.10
Classifier: Programming Language :: Python :: 3.11
Classifier: Programming Language :: Python :: 3.12
Classifier: Programming Language :: Python :: 3.13
Classifier: License :: OSI Approved :: MIT License
Classifier: Topic :: Office/Business :: Financial :: Investment
Classifier: Topic :: Software Development :: Libraries :: Python Modules
Requires-Python: >=3.6, <4.0
License-File: LICENSE
Requires-Dist: pandas>=1.3.0
Requires-Dist: numpy>=1.20.0
Requires-Dist: matplotlib>=3.4.0
Requires-Dist: coinmetrics-api-client>=2024.2.6.16
Requires-Dist: pytest>=6.2.0
Requires-Dist: pandas_datareader>=0.10.0
Requires-Dist: scipy>=1.6.0
Requires-Dist: psutil>=5.8.0
Requires-Dist: bandit>=1.7.0
Requires-Dist: safety>=2.0.0
Requires-Dist: pylint>=3.0.0
Requires-Dist: pytest-cov>=6.0.0
Dynamic: author
Dynamic: author-email
Dynamic: classifier
Dynamic: description
Dynamic: description-content-type
Dynamic: home-page
Dynamic: license-file
Dynamic: project-url
Dynamic: requires-dist
Dynamic: requires-python
Dynamic: summary
